fastapi_security_typeform/__init__.py
fastapi_security_typeform/custom_types.py
fastapi_security_typeform/hash_methods.py
fastapi_security_typeform/py.typed
fastapi_security_typeform/security.py
fastapi_security_typeform-1.0.1.dist-info/LICENSE
fastapi_security_typeform-1.0.1.dist-info/WHEEL
fastapi_security_typeform-1.0.1.dist-info/METADATA
fastapi_security_typeform-1.0.1.dist-info/RECORD
