Metadata-Version: 2.1
Name: fastapi-security-typeform
Version: 1.0.1
Summary: 
Home-page: https://github.com/piterpy-meetup/fastapi-security-typeform
License: MIT
Keywords: fastapi,fastapi security,typeform,signature header,http signatures,typeform webhhok,hmac sha256
Author: Dima Boger
Author-email: meetup@piterpy.ru
Requires-Python: >=3.6
Classifier: License :: OSI Approved :: MIT License
Classifier: Programming Language :: Python :: 3
Classifier: Programming Language :: Python :: 3.6
Classifier: Programming Language :: Python :: 3.7
Classifier: Programming Language :: Python :: 3.8
Requires-Dist: fastapi
Project-URL: Repository, https://github.com/piterpy-meetup/fastapi-security-typeform
